kagglerecipes/__init__.py
kagglerecipes/_nbdev.py
kagglerecipes/data.py
kagglerecipes/preprocess.py
kagglerecipes/utils.py
kagglerecipes/wandb_utils.py
kagglerecipes/wandb_viz.py
kagglerecipes-0.0.5.dist-info/LICENSE
kagglerecipes-0.0.5.dist-info/METADATA
kagglerecipes-0.0.5.dist-info/WHEEL
kagglerecipes-0.0.5.dist-info/entry_points.txt
kagglerecipes-0.0.5.dist-info/top_level.txt
kagglerecipes-0.0.5.dist-info/RECORD
