Metadata-Version: 2.1
Name: kagglerecipes
Version: 0.0.5
Summary: Useful code for different Kaggle competitions. Currently covering RSNA-MICCAI Brain Tumor Radiogenomic Classification Kaggle competition.
Home-page: https://github.com/ayulockin/kagglerecipes/tree/main/
Author: W&B Internal Team
Author-email: mein2work@gmail.com
License: MIT License
Keywords: wandb kaggle-competition brain-tumor-classification
Platform: UNKNOWN
Classifier: Development Status :: 3 - Alpha
Classifier: Intended Audience :: Developers
Classifier: Natural Language :: English
Classifier: Programming Language :: Python :: 3.6
Classifier: Programming Language :: Python :: 3.7
Classifier: Programming Language :: Python :: 3.8
Classifier: License :: OSI Approved :: MIT License
Requires-Python: >=3.6
Requires-Dist: pip
Requires-Dist: packaging
Requires-Dist: torch (>=1.7.0)
Requires-Dist: tensorflow (>=2.4.1)
Requires-Dist: fastcore (>=1.3.26)
Requires-Dist: albumentations (>=1.0.3)
Requires-Dist: wandb (>=0.12.1)
Requires-Dist: pydicom
Requires-Dist: SimpleITK
Requires-Dist: mpire
Requires-Dist: pandas
Provides-Extra: dev
Requires-Dist: nbverbose ; extra == 'dev'
Requires-Dist: nbconvert (==5.6.1) ; extra == 'dev'
Requires-Dist: jupyter-client (==6.1.2) ; extra == 'dev'
